aws_lambda_layer_cli/VERSION.txt
aws_lambda_layer_cli/__init__.py
aws_lambda_layer_cli/cli.py
aws_lambda_layer_cli/assets/__init__.py
aws_lambda_layer_cli/assets/aws-lambda-layer-cli
aws_lambda_layer_cli/assets/create_nodejs_layer.sh
aws_lambda_layer_cli/assets/create_python_layer.sh
aws_lambda_layer_cli/assets/create_wheel_layer.sh
aws_lambda_layer_cli/assets/uninstall.sh
aws_lambda_layer_cli/completion/__init__.py
aws_lambda_layer_cli/completion/aws-lambda-layer-completion.bash
aws_lambda_layer_cli/completion/aws-lambda-layer-completion.zsh
aws_lambda_layer_cli-2.2.0.dist-info/licenses/LICENSE
aws_lambda_layer_cli-2.2.0.dist-info/METADATA
aws_lambda_layer_cli-2.2.0.dist-info/WHEEL
aws_lambda_layer_cli-2.2.0.dist-info/entry_points.txt
aws_lambda_layer_cli-2.2.0.dist-info/top_level.txt
aws_lambda_layer_cli-2.2.0.dist-info/RECORD
