Metadata-Version: 2.4
Name: aws-lambda-layer-cli
Version: 2.2.0
Summary: CLI tool for creating and publishing AWS Lambda layers for Node.js and Python.
License-Expression: MIT
Project-URL: Source, https://github.com/yukcw/aws-lambda-layer-cli
Project-URL: Issues, https://github.com/yukcw/aws-lambda-layer-cli/issues
Classifier: Programming Language :: Python :: 3
Classifier: Programming Language :: Python :: 3 :: Only
Classifier: Environment :: Console
Requires-Python: >=3.8
License-File: LICENSE
Dynamic: license-file
